ds_toolbox/__init__.py
ds_toolbox/econometrics/causal_regression.py
ds_toolbox/ml/__init__.py
ds_toolbox/ml/evaluator.py
ds_toolbox/spark_utils.py
ds_toolbox/statistics.py
ds_toolbox-0.2.0.dist-info/WHEEL
ds_toolbox-0.2.0.dist-info/METADATA
ds_toolbox-0.2.0.dist-info/RECORD
